setup.cfg
setup.py
degenerate/__init__.py
degenerate/duoimpl.py
degenerate/duosync.py
degenerate/roulete.py
degenerate/tsunami.py
degenerate.egg-info/PKG-INFO
degenerate.egg-info/SOURCES.txt
degenerate.egg-info/dependency_links.txt
degenerate.egg-info/pbr.json
degenerate.egg-info/top_level.txt