Metadata-Version: 1.0
Name: degenerate
Version: 0.3
Summary: Write only async code and use for both async and aync
Home-page: git@github.com:hayk91/degenerate.git
Author: UNKNOWN
Author-email: UNKNOWN
License: MIT
Platform: UNKNOWN
